kalabash_webmail/__init__.py
kalabash_webmail/apps.py
kalabash_webmail/constants.py
kalabash_webmail/exceptions.py
kalabash_webmail/forms.py
kalabash_webmail/handlers.py
kalabash_webmail/kbash_extension.py
kalabash_webmail/urls.py
kalabash_webmail/validators.py
kalabash_webmail/views.py
kalabash_webmail/lib/__init__.py
kalabash_webmail/lib/attachments.py
kalabash_webmail/lib/fetch_parser.py
kalabash_webmail/lib/imapemail.py
kalabash_webmail/lib/imapheader.py
kalabash_webmail/lib/imaputils.py
kalabash_webmail/lib/rfc6266.py
kalabash_webmail/lib/sendmail.py
kalabash_webmail/lib/signature.py
kalabash_webmail/lib/utils.py
kalabash_webmail/locale/cs_CZ/LC_MESSAGES/django.mo
kalabash_webmail/locale/cs_CZ/LC_MESSAGES/django.po
kalabash_webmail/locale/cs_CZ/LC_MESSAGES/djangojs.mo
kalabash_webmail/locale/cs_CZ/LC_MESSAGES/djangojs.po
kalabash_webmail/locale/de/LC_MESSAGES/django.mo
kalabash_webmail/locale/de/LC_MESSAGES/django.po
kalabash_webmail/locale/de/LC_MESSAGES/djangojs.mo
kalabash_webmail/locale/de/LC_MESSAGES/djangojs.po
kalabash_webmail/locale/el_GR/LC_MESSAGES/django.mo
kalabash_webmail/locale/el_GR/LC_MESSAGES/django.po
kalabash_webmail/locale/el_GR/LC_MESSAGES/djangojs.mo
kalabash_webmail/locale/el_GR/LC_MESSAGES/djangojs.po
kalabash_webmail/locale/en/LC_MESSAGES/django.mo
kalabash_webmail/locale/en/LC_MESSAGES/django.po
kalabash_webmail/locale/en/LC_MESSAGES/djangojs.mo
kalabash_webmail/locale/en/LC_MESSAGES/djangojs.po
kalabash_webmail/locale/es/LC_MESSAGES/django.mo
kalabash_webmail/locale/es/LC_MESSAGES/django.po
kalabash_webmail/locale/es/LC_MESSAGES/djangojs.mo
kalabash_webmail/locale/es/LC_MESSAGES/djangojs.po
kalabash_webmail/locale/fr/LC_MESSAGES/django.mo
kalabash_webmail/locale/fr/LC_MESSAGES/django.po
kalabash_webmail/locale/fr/LC_MESSAGES/djangojs.mo
kalabash_webmail/locale/fr/LC_MESSAGES/djangojs.po
kalabash_webmail/locale/it/LC_MESSAGES/django.mo
kalabash_webmail/locale/it/LC_MESSAGES/django.po
kalabash_webmail/locale/it/LC_MESSAGES/djangojs.mo
kalabash_webmail-1.9.0.dist-info/LICENSE
kalabash_webmail-1.9.0.dist-info/METADATA
kalabash_webmail-1.9.0.dist-info/WHEEL
kalabash_webmail-1.9.0.dist-info/top_level.txt
kalabash_webmail-1.9.0.dist-info/RECORD
